sem-3-labs/dsdl/lab2/q2a.v
module q2a(b, c, d, f);
	input b, c, d;
	output f;
	assign f = (b | c) & (~b | d);
endmodule

sem-3-labs/dsdl/lab2/q2a_tb.v
`timescale 1ns/1ns
`include "q2a.v"

module q2a_tb();
reg b, c, d;
wire f;

q2a q1(b, c, d, f);
initial
begin

       $dumpfile("q2a_tb.vcd");
       $dumpvars(0, q2a_tb);
       
       b=1'b0; c=1'b0; d=1'b0;
       #20;
       
       b=1'b0; c=1'b0; d=1'b1;
       #20;
       
       b=1'b0; c=1'b1; d=1'b0;
       #20;
       
       b=1'b0; c=1'b1; d=1'b1;
       #20;
       
       b=1'b1; c=1'b0; d=1'b0;
       #20;
       
       b=1'b1; c=1'b0; d=1'b1;
       #20;
       
       b=1'b1; c=1'b1; d=1'b0;
       #20;
       
       b=1'b1; c=1'b1; d=1'b1;
       #20;
       
       $display("Test complete");
end

endmodule

sem-3-labs/dsdl/lab2/q2a_tb.vcd
$date
	Thu Sep  1 10:11:17 2022
$end
$version
	Icarus Verilog
$end
$timescale
	1ns
$end
$scope module q2a_tb $end
$var wire 1 ! f $end
$var reg 1 " b $end
$var reg 1 # c $end
$var reg 1 $ d $end
$scope module q1 $end
$var wire 1 " b $end
$var wire 1 # c $end
$var wire 1 $ d $end
$var wire 1 ! f $end
$upscope $end
$upscope $end
$enddefinitions $end
#0
$dumpvars
0$
0#
0"
0!
$end
#20
1$
#40
1!
0$
1#
#60
1$
#80
0!
0$
0#
1"
#100
1!
1$
#120
0!
0$
1#
#140
1!
1$
