dsdl/lab3/q1.v
module q1(a, b, c, d, f);
   input a, b, c, d;
   output f;
   nand(g,b,b);
   nand(h,d,d);
   nand(i,a,g);
   nand(j,c,h);
   nand(k,i,j);
   nand(f,k,k);
endmodule

dsdl/lab3/q1_tb.v
`timescale 1ns/1ns
`include "q1.v"

module q1_tb();
reg a, b, c, d;
wire f;

q1 q1(a, b, c, d, f);
initial
begin

       $dumpfile("q1_tb.vcd");
       $dumpvars(0, q1_tb);
       
       a=1'b0; b=1'b0; c=1'b0; d=1'b0;
       #20;
       
       a=1'b0; b=1'b0; c=1'b0; d=1'b1;
       #20;
       
       a=1'b0; b=1'b0; c=1'b1; d=1'b0;
       #20;
       
       a=1'b0; b=1'b0; c=1'b1; d=1'b1;
       #20;
       
       a=1'b0; b=1'b1; c=1'b0; d=1'b0;
       #20;
       
       a=1'b0; b=1'b1; c=1'b0; d=1'b1;
       #20;
       
       a=1'b0; b=1'b1; c=1'b1; d=1'b0;
       #20;
       
       a=1'b0; b=1'b1; c=1'b1; d=1'b1;
       #20;
       
       a=1'b1; b=1'b0; c=1'b0; d=1'b0;
       #20;
       
       a=1'b1; b=1'b0; c=1'b0; d=1'b1;
       #20;
       
       a=1'b1; b=1'b0; c=1'b1; d=1'b0;
       #20;
       
       a=1'b1; b=1'b0; c=1'b1; d=1'b1;
       #20;
       
       a=1'b1; b=1'b1; c=1'b0; d=1'b0;
       #20;
       
       a=1'b1; b=1'b1; c=1'b0; d=1'b1;
       #20;
       
       a=1'b1; b=1'b1; c=1'b1; d=1'b0;
       #20;
       
       a=1'b1; b=1'b1; c=1'b1; d=1'b1;
       #20;
       
       $display("Test complete");
end

endmodule

sem-3-labs/dsdl/lab3/q1_tb.vcd
$date
	Thu Sep  8 10:22:14 2022
$end
$version
	Icarus Verilog
$end
$timescale
	1ns
$end
$scope module q1_tb $end
$var wire 1 ! f $end
$var reg 1 " a $end
$var reg 1 # b $end
$var reg 1 $ c $end
$var reg 1 % d $end
$scope module q1 $end
$var wire 1 " a $end
$var wire 1 # b $end
$var wire 1 $ c $end
$var wire 1 % d $end
$var wire 1 ! f $end
$var wire 1 & g $end
$var wire 1 ' h $end
$var wire 1 ( i $end
$var wire 1 ) j $end
$var wire 1 * k $end
$upscope $end
$upscope $end
$enddefinitions $end
#0
$dumpvars
0*
1)
1(
1'
1&
0%
0$
0#
0"
1!
$end
#20
0'
1%
#40
0!
1*
0)
1'
0%
1$
#60
1!
0*
1)
0'
1%
#80
1'
0&
0%
0$
1#
#100
0'
1%
#120
0!
1*
0)
1'
0%
1$
#140
1!
0*
1)
0'
1%
#160
0!
1*
0(
1'
1&
0%
0$
0#
1"
#180
0'
1%
#200
0)
1'
0%
1$
#220
1)
0'
1%
#240
1!
0*
1(
1'
0&
0%
0$
1#
#260
0'
1%
#280
0!
1*
0)
1'
0%
1$
#300
1!
0*
1)
0'
1%
