sem-3-labs/dsdl/lab8/q1.v
module q1(w,e,y);
	input [2:0] w;
	input e;
	output [0:7] y;
	wire t1,t2;
	assign t1 = ~w[2] & e;
	assign t2 = w[2] & e;

	d24 stage0(w[1:0],t1,y[0:3]);
	d24 stage1(w[1:0],t2,y[4:7]);

endmodule

module d24(w,e,y);
	input [1:0] w;
	input e;
	output reg [0:3] y;
	integer x;
	always @(w or e)
	for (x = 0; x <= 3; x=x+1)
		if ((w==x) && (e == 1))
			y[x] = 1;
		else
			y[x] = 0;
endmodule

dsdl/lab8/q1_tb.v
`timescale 1ns/1ns
`include "q1.v"

module q1_tb();
reg [2:0] w;
reg e;
wire [0:7] y;

q1 q1(w,e,y);
initial
begin
    $dumpfile("q1_tb.vcd");
    $dumpvars(0,q1_tb);
    e = 1;
    w = 3'b000;#20;
    w = 3'b001;#20;
    w = 3'b010;#20;
    w = 3'b011;#20;
    w = 3'b100;#20;
    w = 3'b101;#20;
    w = 3'b110;#20;
    w = 3'b111;#20;

    $display("Test Complete");

end
endmodule

dsdl/lab8/q1_tb.vcd
$date
	Thu Oct 20 09:59:10 2022
$end
$version
	Icarus Verilog
$end
$timescale
	1ns
$end
$scope module q1_tb $end
$var wire 8 ! y [0:7] $end
$var reg 1 " e $end
$var reg 3 # w [2:0] $end
$scope module q1 $end
$var wire 1 " e $end
$var wire 1 $ t1 $end
$var wire 1 % t2 $end
$var wire 3 & w [2:0] $end
$var wire 8 ' y [0:7] $end
$scope module stage0 $end
$var wire 1 $ e $end
$var wire 2 ( w [1:0] $end
$var reg 4 ) y [0:3] $end
$var integer 32 * x [31:0] $end
$upscope $end
$scope module stage1 $end
$var wire 1 % e $end
$var wire 2 + w [1:0] $end
$var reg 4 , y [0:3] $end
$var integer 32 - x [31:0] $end
$upscope $end
$upscope $end
$upscope $end
$enddefinitions $end
#0
$dumpvars
b100 -
b0 ,
b0 +
b100 *
b1000 )
b0 (
b10000000 '
b0 &
0%
1$
b0 #
1"
b10000000 !
$end
#20
b1000000 !
b1000000 '
b100 )
b100 *
b100 -
b1 (
b1 +
b1 #
b1 &
#40
b100000 !
b100000 '
b10 )
b100 *
b100 -
b10 (
b10 +
b10 #
b10 &
#60
b10000 !
b10000 '
b1 )
b100 *
b100 -
b11 (
b11 +
b11 #
b11 &
#80
0$
b1000 ,
1%
b1000 !
b1000 '
b0 )
b100 *
b100 -
b0 (
b0 +
b100 #
b100 &
#100
b100 *
b100 !
b100 '
b100 ,
b100 -
b1 (
b1 +
b101 #
b101 &
#120
b100 *
b10 !
b10 '
b10 ,
b100 -
b10 (
b10 +
b110 #
b110 &
#140
b100 *
b1 !
b1 '
b1 ,
b100 -
b11 (
b11 +
b111 #
b111 &
