dsdl/lab9/q1.v
module q1(w,f);
	input [3:0] w;
	output f;
	wire [15:0] k;
	d416 s0(w, k);
	assign f = k[1] | k[3] | k[6] | k[7] | k[9] | k[14] | k[15];	
endmodule

module d416(w,f);
	input [3:0] w;
	output reg [15:0] f;
	integer i;
	always@(w)
	begin
		for(i=0;i<16;i=i+1)
		begin
			if(w == i)
				f[i] = 1;
			else
				f[i] = 0;
		end
	end
endmodule

dsdl/lab9/q1_tb.v
`timescale 1ns/1ns
`include "q1.v"

module q1_tb();
reg [3:0] w;
wire f;
integer i;

q1 q1(w,f);
initial
begin
	$dumpfile("q1_tb.vcd");
	$dumpvars(0,q1_tb);
	
	for(i=0;i<16;i=i+1)
	begin 
		w=i; #20;
	end
	
	$display("Test Complete");
end 
endmodule

sem-3-labs/dsdl/lab9/q1_tb.vcd
$date
	Thu Oct 27 10:06:19 2022
$end
$version
	Icarus Verilog
$end
$timescale
	1ns
$end
$scope module q1_tb $end
$var wire 1 ! f $end
$var reg 4 " w [3:0] $end
$var integer 32 # i [31:0] $end
$scope module q1 $end
$var wire 1 ! f $end
$var wire 4 $ w [3:0] $end
$var wire 16 % k [15:0] $end
$scope module s0 $end
$var wire 4 & w [3:0] $end
$var reg 16 ' f [15:0] $end
$var integer 32 ( i [31:0] $end
$upscope $end
$upscope $end
$upscope $end
$enddefinitions $end
#0
$dumpvars
b10000 (
b1 '
b0 &
b1 %
b0 $
b0 #
b0 "
0!
$end
#20
1!
b10 %
b10 '
b10000 (
b1 "
b1 $
b1 &
b1 #
#40
0!
b100 %
b100 '
b10000 (
b10 "
b10 $
b10 &
b10 #
#60
1!
b1000 %
b1000 '
b10000 (
b11 "
b11 $
b11 &
b11 #
#80
0!
b10000 %
b10000 '
b10000 (
b100 "
b100 $
b100 &
b100 #
#100
b100000 %
b100000 '
b10000 (
b101 "
b101 $
b101 &
b101 #
#120
1!
b1000000 %
b1000000 '
b10000 (
b110 "
b110 $
b110 &
b110 #
#140
b10000000 %
b10000000 '
b10000 (
b111 "
b111 $
b111 &
b111 #
#160
0!
b100000000 %
b100000000 '
b10000 (
b1000 "
b1000 $
b1000 &
b1000 #
#180
1!
b1000000000 %
b1000000000 '
b10000 (
b1001 "
b1001 $
b1001 &
b1001 #
#200
0!
b10000000000 %
b10000000000 '
b10000 (
b1010 "
b1010 $
b1010 &
b1010 #
#220
b100000000000 %
b100000000000 '
b10000 (
b1011 "
b1011 $
b1011 &
b1011 #
#240
b1000000000000 %
b1000000000000 '
b10000 (
b1100 "
b1100 $
b1100 &
b1100 #
#260
b10000000000000 %
b10000000000000 '
b10000 (
b1101 "
b1101 $
b1101 &
b1101 #
#280
1!
b100000000000000 %
b100000000000000 '
b10000 (
b1110 "
b1110 $
b1110 &
b1110 #
#300
b1000000000000000 %
b1000000000000000 '
b10000 (
b1111 "
b1111 $
b1111 &
b1111 #
#320
b10000 #
