dsdl/lab9/q2.v
module q2(w,f,g,h);
	input [3:0] w;
	output f,g,h;
	wire [15:0] z;
	d416 s0(w,1'b1,z);
	
	assign f = z[11] | z[10] | z[7] | z[3] | z[14] | z[6];
	assign g = z[14] | z[10] | z[1] | z[0];
	assign h = z[1] | z[0] | z[15] | z[14] | z[7] | z[3];
endmodule
	

module d416(w,En,f);
	input [3:0] w;
	input En;
	output [15:0] f;
	wire [3:0] c;
	d24 stage0(w[3:2],En,c);
	d24 stage1(w[1:0],c[0],f[3:0]);
	d24 stage2(w[1:0],c[1],f[7:4]);
	d24 stage3(w[1:0],c[2],f[11:8]);
	d24 stage4(w[1:0],c[3],f[15:12]);
endmodule

module d24(w,En,f);	
	input [1:0] w;
	input En;
	output reg [3:0] f;
	always@(w,En)
	begin
		case(En)
		  0: f = 4'b0000;
		  1:
		  begin
		  	case(w)
		  		0:f=4'b0001;
		  		1:f=4'b0010;
		  		2:f=4'b0100;
		  		3:f=4'b1000;
		  	endcase
		  end
		endcase
	end
endmodule

sem-3-labs/dsdl/lab9/q2_tb.v
`timescale 1ns/1ns
`include "q2.v"

module q2_tb();
reg [3:0] w;
wire f,g,h;
integer i;

q2 q2(w,f,g,h);
initial
begin
	$dumpfile("q2_tb.vcd");
	$dumpvars(0,q2_tb);
	
	for(i=0;i<16;i=i+1)
	begin 
		w=i; #20;
	end
	
	$display("Test Complete");
end 
endmodule

dsdl/lab9/q2_tb.vcd
$date
	Thu Oct 27 10:26:48 2022
$end
$version
	Icarus Verilog
$end
$timescale
	1ns
$end
$scope module q2_tb $end
$var wire 1 ! h $end
$var wire 1 " g $end
$var wire 1 # f $end
$var reg 4 $ w [3:0] $end
$var integer 32 % i [31:0] $end
$scope module q2 $end
$var wire 1 # f $end
$var wire 1 " g $end
$var wire 1 ! h $end
$var wire 4 & w [3:0] $end
$var wire 16 ' z [15:0] $end
$scope module s0 $end
$var wire 1 ( En $end
$var wire 4 ) w [3:0] $end
$var wire 16 * f [15:0] $end
$var wire 4 + c [3:0] $end
$scope module stage0 $end
$var wire 1 ( En $end
$var wire 2 , w [1:0] $end
$var reg 4 - f [3:0] $end
$upscope $end
$scope module stage1 $end
$var wire 1 . En $end
$var wire 2 / w [1:0] $end
$var reg 4 0 f [3:0] $end
$upscope $end
$scope module stage2 $end
$var wire 1 1 En $end
$var wire 2 2 w [1:0] $end
$var reg 4 3 f [3:0] $end
$upscope $end
$scope module stage3 $end
$var wire 1 4 En $end
$var wire 2 5 w [1:0] $end
$var reg 4 6 f [3:0] $end
$upscope $end
$scope module stage4 $end
$var wire 1 7 En $end
$var wire 2 8 w [1:0] $end
$var reg 4 9 f [3:0] $end
$upscope $end
$upscope $end
$upscope $end
$upscope $end
$enddefinitions $end
#0
$dumpvars
b0 9
b0 8
07
b0 6
b0 5
04
b0 3
b0 2
01
b1 0
b0 /
1.
b1 -
b0 ,
b1 +
b1 *
b0 )
1(
b1 '
b0 &
b0 %
b0 $
0#
1"
1!
$end
#20
b10 '
b10 *
b10 0
b1 /
b1 2
b1 5
b1 8
b1 $
b1 &
b1 )
b1 %
#40
0!
0"
b100 '
b100 *
b100 0
b10 /
b10 2
b10 5
b10 8
b10 $
b10 &
b10 )
b10 %
#60
1#
1!
b1000 '
b1000 *
b1000 0
b11 /
b11 2
b11 5
b11 8
b11 $
b11 &
b11 )
b11 %
#80
0#
b1 3
0!
0"
11
0.
b10 +
b10 -
b10000 '
b10000 *
b0 0
b1 ,
b0 /
b0 2
b0 5
b0 8
b100 $
b100 &
b100 )
b100 %
#100
b100000 '
b100000 *
b10 3
b1 /
b1 2
b1 5
b1 8
b101 $
b101 &
b101 )
b101 %
#120
1#
b1000000 '
b1000000 *
b100 3
b10 /
b10 2
b10 5
b10 8
b110 $
b110 &
b110 )
b110 %
#140
1!
1#
b10000000 '
b10000000 *
b1000 3
b11 /
b11 2
b11 5
b11 8
b111 $
b111 &
b111 )
b111 %
#160
0#
0!
b1 6
14
01
b100 +
b100 -
b100000000 '
b100000000 *
b0 3
b10 ,
b0 /
b0 2
b0 5
b0 8
b1000 $
b1000 &
b1000 )
b1000 %
#180
b1000000000 '
b1000000000 *
b10 6
b1 /
b1 2
b1 5
b1 8
b1001 $
b1001 &
b1001 )
b1001 %
#200
1#
1"
b10000000000 '
b10000000000 *
b100 6
b10 /
b10 2
b10 5
b10 8
b1010 $
b1010 &
b1010 )
b1010 %
#220
0"
b100000000000 '
b100000000000 *
b1000 6
b11 /
b11 2
b11 5
b11 8
b1011 $
b1011 &
b1011 )
b1011 %
#240
0#
b1 9
17
04
b1000 +
b1000 -
b1000000000000 '
b1000000000000 *
b0 6
b11 ,
b0 /
b0 2
b0 5
b0 8
b1100 $
b1100 &
b1100 )
b1100 %
#260
b10000000000000 '
b10000000000000 *
b10 9
b1 /
b1 2
b1 5
b1 8
b1101 $
b1101 &
b1101 )
b1101 %
#280
1!
1"
1#
b100000000000000 '
b100000000000000 *
b100 9
b10 /
b10 2
b10 5
b10 8
b1110 $
b1110 &
b1110 )
b1110 %
#300
0"
0#
b1000000000000000 '
b1000000000000000 *
b1000 9
b11 /
b11 2
b11 5
b11 8
b1111 $
b1111 &
b1111 )
b1111 %
#320
b10000 %
