sem-3-labs/dsdl/lab3/q4.v
module q4(a, b, c, d, f);
   input a, b, c, d;
   output f;
   nor(g,a,a);
   nor(h,c,c);
   nor(i,d,d);
   nor(j,g,h);
   nor(f,i,j);
endmodule

dsdl/lab3/q4_tb.v
`timescale 1ns/1ns
`include "q4.v"

module q4_tb();
reg a, b, c, d;
wire f;

q4 q4(a, b, c, d, f);
initial
begin

       $dumpfile("q4_tb.vcd");
       $dumpvars(0, q4_tb);
       
       a=1'b0; b=1'b0; c=1'b0; d=1'b0;
       #20;
       
       a=1'b0; b=1'b0; c=1'b0; d=1'b1;
       #20;
       
       a=1'b0; b=1'b0; c=1'b1; d=1'b0;
       #20;
       
       a=1'b0; b=1'b0; c=1'b1; d=1'b1;
       #20;
       
       a=1'b0; b=1'b1; c=1'b0; d=1'b0;
       #20;
       
       a=1'b0; b=1'b1; c=1'b0; d=1'b1;
       #20;
       
       a=1'b0; b=1'b1; c=1'b1; d=1'b0;
       #20;
       
       a=1'b0; b=1'b1; c=1'b1; d=1'b1;
       #20;
       
       a=1'b1; b=1'b0; c=1'b0; d=1'b0;
       #20;
       
       a=1'b1; b=1'b0; c=1'b0; d=1'b1;
       #20;
       
       a=1'b1; b=1'b0; c=1'b1; d=1'b0;
       #20;
       
       a=1'b1; b=1'b0; c=1'b1; d=1'b1;
       #20;
       
       a=1'b1; b=1'b1; c=1'b0; d=1'b0;
       #20;
       
       a=1'b1; b=1'b1; c=1'b0; d=1'b1;
       #20;
       
       a=1'b1; b=1'b1; c=1'b1; d=1'b0;
       #20;
       
       a=1'b1; b=1'b1; c=1'b1; d=1'b1;
       #20;
       
       $display("Test complete");
end

endmodule

dsdl/lab3/q4_tb.vcd
$date
	Thu Sep  8 11:19:51 2022
$end
$version
	Icarus Verilog
$end
$timescale
	1ns
$end
$scope module q4_tb $end
$var wire 1 ! f $end
$var reg 1 " a $end
$var reg 1 # b $end
$var reg 1 $ c $end
$var reg 1 % d $end
$scope module q4 $end
$var wire 1 " a $end
$var wire 1 # b $end
$var wire 1 $ c $end
$var wire 1 % d $end
$var wire 1 ! f $end
$var wire 1 & g $end
$var wire 1 ' h $end
$var wire 1 ( i $end
$var wire 1 ) j $end
$upscope $end
$upscope $end
$enddefinitions $end
#0
$dumpvars
0)
1(
1'
1&
0%
0$
0#
0"
0!
$end
#20
1!
0(
1%
#40
0!
1(
0'
0%
1$
#60
1!
0(
1%
#80
0!
1(
1'
0%
0$
1#
#100
1!
0(
1%
#120
0!
1(
0'
0%
1$
#140
1!
0(
1%
#160
0!
1(
1'
0&
0%
0$
0#
1"
#180
1!
0(
1%
#200
0!
1)
1(
0'
0%
1$
#220
0(
1%
#240
0)
1(
1'
0%
0$
1#
#260
1!
0(
1%
#280
0!
1)
1(
0'
0%
1$
#300
0(
1%
